snakegram_up/__init__.py
snakegram_up-1.1.1.dist-info/METADATA
snakegram_up-1.1.1.dist-info/WHEEL
snakegram_up-1.1.1.dist-info/top_level.txt
snakegram_up-1.1.1.dist-info/RECORD
