Metadata-Version: 2.4
Name: snakegram_up
Version: 1.1.1
Summary: Full-featured Telegram client library for Python 3
Home-page: https://github.com/amirwolf5122/snakegram_up
Author: Amir:3
Author-email: amirwolf512@gmail.com
License: MIT
Keywords: telegram api chat client library messaging mtproto
Classifier: Development Status :: 5 - Production/Stable
Classifier: Intended Audience :: Developers
Classifier: Topic :: Communications :: Chat
Classifier: License :: OSI Approved :: MIT License
Classifier: Programming Language :: Python :: 3
Classifier: Programming Language :: Python :: 3.5
Classifier: Programming Language :: Python :: 3.6
Classifier: Programming Language :: Python :: 3.7
Classifier: Programming Language :: Python :: 3.8
Requires-Python: >=3.5
Dynamic: author
Dynamic: author-email
Dynamic: classifier
Dynamic: description
Dynamic: description-content-type
Dynamic: home-page
Dynamic: keywords
Dynamic: license
Dynamic: requires-python
Dynamic: summary
